metadata_filter/__init__.py
metadata_filter/filters.py
metadata_filter/rules.py
tests/__init__.py
tests/test_spotify.py
metadata_filter-0.1.0.dist-info/LICENSE
metadata_filter-0.1.0.dist-info/METADATA
metadata_filter-0.1.0.dist-info/WHEEL
metadata_filter-0.1.0.dist-info/top_level.txt
metadata_filter-0.1.0.dist-info/RECORD
