Metadata-Version: 2.1
Name: metadata-filter
Version: 0.1.0
Summary: Metadata filters for scrobblers
Home-page: https://github.com/YodaEmbedding/metadata-filter
Author: Mateen Ulhaq
Author-email: mulhaq2005@gmail.com
License: MIT
Platform: UNKNOWN
